espocrm/__init__.py
espocrm/client.py
espocrm/config.py
espocrm/exceptions.py
espocrm/py.typed
espocrm/auth/__init__.py
espocrm/auth/api_key.py
espocrm/auth/base.py
espocrm/auth/basic.py
espocrm/auth/hmac.py
espocrm/clients/__init__.py
espocrm/clients/base.py
espocrm/clients/crud.py
espocrm/models/__init__.py
espocrm/models/base.py
espocrm/models/entities.py
espocrm/models/requests.py
espocrm/models/responses.py
espocrm/models/search.py
espocrm/utils/__init__.py
espocrm/utils/helpers.py
espocrm/utils/http.py
espocrm/utils/serializers.py
espocrm/utils/validators.py
espocrm_client-0.2.0.dist-info/licenses/LICENSE
espocrm_client-0.2.0.dist-info/METADATA
espocrm_client-0.2.0.dist-info/WHEEL
espocrm_client-0.2.0.dist-info/entry_points.txt
espocrm_client-0.2.0.dist-info/top_level.txt
espocrm_client-0.2.0.dist-info/RECORD
