Metadata-Version: 2.4
Name: espocrm-client
Version: 0.2.0
Summary: Modern, type-safe and comprehensive EspoCRM API client library for Python
Author-email: EspoCRM Python Client Team <support@espocrm-python-client.com>
Maintainer-email: EspoCRM Python Client Team <support@espocrm-python-client.com>
License: MIT
Project-URL: Homepage, https://github.com/espocrm/espocrm-client
Project-URL: Documentation, https://espocrm-client.readthedocs.io
Project-URL: Repository, https://github.com/espocrm/espocrm-client.git
Project-URL: Issues, https://github.com/espocrm/espocrm-client/issues
Project-URL: Changelog, https://github.com/espocrm/espocrm-client/blob/main/CHANGELOG.md
Project-URL: Bug Reports, https://github.com/espocrm/espocrm-client/issues
Project-URL: Feature Requests, https://github.com/espocrm/espocrm-client/issues/new?template=feature_request.md
Project-URL: Source Code, https://github.com/espocrm/espocrm-client
Project-URL: Download, https://pypi.org/project/espocrm-client/
Project-URL: Funding, https://github.com/sponsors/espocrm
Keywords: espocrm,api,client,crm,rest,api-client,customer-relationship-management,business-automation,sales-management,lead-management,contact-management,opportunity-management,type-safe,pydantic,structured-logging
Classifier: Development Status :: 4 - Beta
Classifier: Intended Audience :: Developers
Classifier: Intended Audience :: System Administrators
Classifier: License :: OSI Approved :: MIT License
Classifier: Operating System :: OS Independent
Classifier: Programming Language :: Python :: 3
Classifier: Programming Language :: Python :: 3.8
Classifier: Programming Language :: Python :: 3.9
Classifier: Programming Language :: Python :: 3.10
Classifier: Programming Language :: Python :: 3.11
Classifier: Programming Language :: Python :: 3.12
Classifier: Programming Language :: Python :: 3 :: Only
Classifier: Topic :: Software Development :: Libraries :: Python Modules
Classifier: Topic :: Internet :: WWW/HTTP :: Dynamic Content
Classifier: Topic :: Internet :: WWW/HTTP
Classifier: Topic :: Office/Business
Classifier: Topic :: Office/Business :: Financial :: Accounting
Classifier: Topic :: Database
Classifier: Topic :: Communications
Classifier: Typing :: Typed
Classifier: Framework :: Pydantic
Classifier: Environment :: Web Environment
Classifier: Natural Language :: English
Classifier: Natural Language :: Turkish
Requires-Python: >=3.8
License-File: LICENSE
Requires-Dist: requests<3.0.0,>=2.31.0
Requires-Dist: pydantic<3.0.0,>=2.5.0
Requires-Dist: structlog<25.0.0,>=23.2.0
Requires-Dist: typing-extensions>=4.8.0; python_version < "3.11"
Provides-Extra: dev
Requires-Dist: pytest>=7.4.0; extra == "dev"
Requires-Dist: pytest-cov>=4.1.0; extra == "dev"
Requires-Dist: pytest-asyncio>=0.21.0; extra == "dev"
Requires-Dist: black>=23.0.0; extra == "dev"
Requires-Dist: isort>=5.12.0; extra == "dev"
Requires-Dist: mypy>=1.7.0; extra == "dev"
Requires-Dist: pre-commit>=3.5.0; extra == "dev"
Requires-Dist: flake8>=6.0.0; extra == "dev"
Requires-Dist: bandit>=1.7.0; extra == "dev"
Provides-Extra: docs
Requires-Dist: mkdocs>=1.5.0; extra == "docs"
Requires-Dist: mkdocs-material>=9.4.0; extra == "docs"
Requires-Dist: mkdocstrings[python]>=0.24.0; extra == "docs"
Provides-Extra: async
Requires-Dist: httpx>=0.25.0; extra == "async"
Requires-Dist: aiofiles>=23.2.0; extra == "async"
Dynamic: license-file
